py_tresos/__init__.py
py_tresos/cli/__init__.py
py_tresos/cli/eb_guide_cli.py
py_tresos/cli/eb_plugin_cli.py
py_tresos/cli/eb_xpath_cli.py
py_tresos/models/__init__.py
py_tresos/models/abstract_folder_mgr.py
py_tresos/models/abstract_info.py
py_tresos/models/guide_folder_mgr.py
py_tresos/models/guide_info.py
py_tresos/models/plugin_folder_mgr.py
py_tresos/models/plugin_info.py
py_tresos/models/xpath_folder_mgr.py
py_tresos/models/xpath_info.py
py_tresos/tpls/guide/.classpath.tpl
py_tresos/tpls/guide/.project.tpl
py_tresos/tpls/guide/build.properties.tpl
py_tresos/tpls/guide/component.ant.tpl
py_tresos/tpls/guide/plugin.xml.tpl
py_tresos/tpls/guide/Java/backend.java.tpl
py_tresos/tpls/guide/Java/constants.java.tpl
py_tresos/tpls/guide/Java/page.java.tpl
py_tresos/tpls/guide/Java/pushevent.java.tpl
py_tresos/tpls/guide/Java/pushoperation.java.tpl
py_tresos/tpls/guide/META-INF/MANIFEST.MF.tpl
py_tresos/tpls/guide/config/Template.xdm.tpl
py_tresos/tpls/plugin/.classpath.tpl
py_tresos/tpls/plugin/.project.tpl
py_tresos/tpls/plugin/build.properties.tpl
py_tresos/tpls/plugin/component.ant.tpl
py_tresos/tpls/plugin/header.h.tpl
py_tresos/tpls/plugin/plugin.xml.tpl
py_tresos/tpls/plugin/source.c.tpl
py_tresos/tpls/plugin/META-INF/MANIFEST.MF.tpl
py_tresos/tpls/plugin/config/Template.xdm.tpl
py_tresos/tpls/plugin/doc/user_manual.md
py_tresos/tpls/plugin/generate_swcd/swcd/Bswmd.arxml
py_tresos/tpls/plugin/generate_swcd/swcd/swc_interface.arxml
py_tresos/tpls/plugin/generate_swcd/swcd/swc_internal.arxml
py_tresos/tpls/plugin/make/defs.mak
py_tresos/tpls/plugin/make/rules.mak
py_tresos/tpls/xpath/.classpath.tpl
py_tresos/tpls/xpath/.project.tpl
py_tresos/tpls/xpath/build.properties.tpl
py_tresos/tpls/xpath/component.ant.tpl
py_tresos/tpls/xpath/plugin.xml.tpl
py_tresos/tpls/xpath/META-INF/MANIFEST.MF.tpl
py_tresos/tpls/xpath/src/XPathFunctions.java.tpl
py_tresos-1.2.1.dist-info/LICENSE
py_tresos-1.2.1.dist-info/METADATA
py_tresos-1.2.1.dist-info/WHEEL
py_tresos-1.2.1.dist-info/entry_points.txt
py_tresos-1.2.1.dist-info/top_level.txt
py_tresos-1.2.1.dist-info/RECORD
