Metadata-Version: 2.1
Name: py-tresos
Version: 1.2.1
Summary: A Python tool for EB Tresos Studio Plugins
Home-page: UNKNOWN
Author: Melodypapa
Author-email: melodypapa@outlook.com
License: MIT
Keywords: EB Tresos Plugin
Platform: UNKNOWN
Classifier: Development Status :: 1 - Planning
Classifier: Environment :: Console
Classifier: Programming Language :: Python :: 3
Classifier: License :: OSI Approved :: MIT License
Classifier: Operating System :: OS Independent
Requires-Python: >=3.5
Requires-Dist: toml
Requires-Dist: jinja2
Provides-Extra: pytest
Requires-Dist: pytest-cov ; extra == 'pytest'
